dbnd_examples_orchestration/__init__.py
dbnd_examples_orchestration/_plugin.py
dbnd_examples_orchestration/conftest.py
dbnd_examples_orchestration/data.py
dbnd_examples_orchestration/dbnd_spark/__init__.py
dbnd_examples_orchestration/dbnd_spark/spark_jvm/pom.xml
dbnd_examples_orchestration/dbnd_spark/spark_jvm/src/main/java/ai/databand/examples/AddDressing.java
dbnd_examples_orchestration/dbnd_spark/spark_jvm/src/main/java/ai/databand/examples/Cut.java
dbnd_examples_orchestration/dbnd_spark/spark_jvm/src/main/java/ai/databand/examples/WordCount.java
dbnd_examples_orchestration/dbnd_spark/spark_jvm/src/main/java/ai/databand/examples/WordCountWithHtml.java
dbnd_examples_orchestration/orchestration/__init__.py
dbnd_examples_orchestration/orchestration/customizations/__init__.py
dbnd_examples_orchestration/orchestration/customizations/custom_decorator.py
dbnd_examples_orchestration/orchestration/customizations/custom_decorator2.py
dbnd_examples_orchestration/orchestration/customizations/custom_logging.py
dbnd_examples_orchestration/orchestration/customizations/custom_marshaller_excel.py
dbnd_examples_orchestration/orchestration/customizations/custom_marshaller_override.py
dbnd_examples_orchestration/orchestration/customizations/custom_output_factory.py
dbnd_examples_orchestration/orchestration/customizations/custom_output_location.py
dbnd_examples_orchestration/orchestration/customizations/custom_paramester_user_object.py
dbnd_examples_orchestration/orchestration/customizations/custom_target.py
dbnd_examples_orchestration/orchestration/customizations/custom_value_type.py
dbnd_examples_orchestration/orchestration/dbnd_airflow/__init__.py
dbnd_examples_orchestration/orchestration/dbnd_airflow/scheduled_dbnd_check.py
dbnd_examples_orchestration/orchestration/dbnd_aws/__init__.py
dbnd_examples_orchestration/orchestration/dbnd_aws/ingest_pipeline.py
dbnd_examples_orchestration/orchestration/dbnd_aws/sync_operators.py
dbnd_examples_orchestration-1.0.30.1.dist-info/LICENSE
dbnd_examples_orchestration-1.0.30.1.dist-info/METADATA
dbnd_examples_orchestration-1.0.30.1.dist-info/WHEEL
dbnd_examples_orchestration-1.0.30.1.dist-info/entry_points.txt
dbnd_examples_orchestration-1.0.30.1.dist-info/top_level.txt
dbnd_examples_orchestration-1.0.30.1.dist-info/RECORD
